tiktrack/__init__.py
tiktrack/core.py
tikTrack-0.1.0.dist-info/LICENSE
tikTrack-0.1.0.dist-info/METADATA
tikTrack-0.1.0.dist-info/WHEEL
tikTrack-0.1.0.dist-info/top_level.txt
tikTrack-0.1.0.dist-info/RECORD
