Metadata-Version: 2.1
Name: tikTrack
Version: 0.1.0
Summary: A simple performance tracking and visualization tool for Python applications
Home-page: https://github.com/yourusername/tikTrack
Author: kezhuanzhai
Author-email: your.email@example.com
Classifier: Programming Language :: Python :: 3
Classifier: License :: OSI Approved :: MIT License
Classifier: Operating System :: OS Independent
Requires-Python: >=3.6
License-File: LICENSE
Requires-Dist: pandas >=1.0.0
Requires-Dist: matplotlib >=3.0.0
